__init__.py
unointerface.py
unointerface-1.0.dist-info/LICENSE
unointerface-1.0.dist-info/METADATA
unointerface-1.0.dist-info/WHEEL
unointerface-1.0.dist-info/top_level.txt
unointerface-1.0.dist-info/RECORD
