Metadata-Version: 2.1
Name: unointerface
Version: 1.0
Summary: An uno interface to use with training an AI or playing a local game of uno
Author: Edward Baker
Project-URL: Homepage, https://github.com/Iridum-png/unointerface
Project-URL: Bug Tracker, https://github.com/Iridum-png/unointerface/issues
Classifier: Programming Language :: Python :: 3
Classifier: License :: OSI Approved :: MIT License
Classifier: Operating System :: OS Independent
Requires-Python: >=3.6
License-File: LICENSE
